peakachu/__init__.py
peakachu/calculate_depth.py
peakachu/call_loops.py
peakachu/peakacluster.py
peakachu/scoreUtils.py
peakachu/score_chromosome.py
peakachu/score_genome.py
peakachu/trainUtils.py
peakachu/train_models.py
peakachu/utils.py
peakachu-2.2.post1.data/scripts/peakachu
peakachu-2.2.post1.dist-info/LICENSE
peakachu-2.2.post1.dist-info/METADATA
peakachu-2.2.post1.dist-info/WHEEL
peakachu-2.2.post1.dist-info/top_level.txt
peakachu-2.2.post1.dist-info/RECORD
