Metadata-Version: 2.1
Name: peakachu
Version: 2.2.post1
Summary: A supervised learning framework for chromatin loop detection in genome-wide contact maps.
Home-page: https://github.com/tariks/peakachu/
Author: Xiaotao Wang and Tarik Salameh
Author-email: wangxiaotao686@gmail.com
Keywords: Hi-C chromatin interaction contact loop peak cooler
Classifier: Programming Language :: Python :: 3.6
Classifier: License :: OSI Approved :: GNU General Public License v3 or later (GPLv3+)
Classifier: Operating System :: POSIX
Classifier: Development Status :: 3 - Alpha
Classifier: Intended Audience :: Science/Research
Classifier: Topic :: Scientific/Engineering :: Bio-Informatics
License-File: LICENSE
